tests/mult_36x36.v
module mult36x36  (
    input clk,
    input rstn,
    input ce,
    input valid_in,
    input signed [35:0] data_a,
    input signed [35:0] data_b,
    output reg valid_out,
    output reg signed  [71:0] mult_result
);
    
always @(posedge clk or negedge rstn) begin
    if(!rstn) begin
        valid_out <= 0;
    end else begin
        valid_out <= valid_in;
    end

    if(!rstn) begin
        mult_result <= 0;
    end else if(ce && valid_in) begin
        mult_result <= $signed(data_a) * $signed(data_b);
    end
end
endmodule

tests/tb_mult36x36_advanced.v
`timescale 1ns/1ps
module tb_mult36x36_advanced;
  reg clk = 0;
  always #5 clk = ~clk; // 10ns period

  reg rstn;
  reg ce;
  reg valid_in;
  reg signed [35:0] data_a;
  reg signed [35:0] data_b;
  wire valid_out;
  wire signed [71:0] mult_result;

  integer i;
  integer errors = 0;
  reg signed [71:0] expected;
  // helper temporaries declared at module scope for Verilog-2001 compatibility
  reg [63:0] r;
  reg [63:0] r1;
  reg [63:0] r2;
  reg signed [35:0] A[0:7];
  reg signed [35:0] B[0:7];
  integer idx;

  // Instantiate DUT
  mult36x36 uut (
    .clk(clk),
    .rstn(rstn),
    .ce(ce),
    .valid_in(valid_in),
    .data_a(data_a),
    .data_b(data_b),
    .valid_out(valid_out),
    .mult_result(mult_result)
  );

  // mode: 0=basic, 1=random, 2=boundary, 3=pipeline
  integer mode = 1;
  integer NV = 256; // number of vectors for random/pipeline
  integer seed = 0;

  // boundary constants for signed 36-bit
  localparam signed [35:0] MAX36 = 36'sd34359738367;
  localparam signed [35:0] MIN36 = -36'sd34359738368;

  initial begin
    // parse plusargs
    if (!$value$plusargs("mode=%d", mode)) mode = 1;
    if (!$value$plusargs("nv=%d", NV)) NV = 256;
    if (!$value$plusargs("seed=%d", seed)) seed = 0;

    if (seed == 0) seed = $random;
    $display("Running advanced mult36x36 TB: mode=%0d nv=%0d seed=%0d", mode, NV, seed);

    $dumpfile("wave.vcd");
    $dumpvars(0, tb_mult36x36_advanced);

    // reset
    rstn = 0; ce = 0; valid_in = 0; data_a = 0; data_b = 0;
    #20; // two clock cycles
    rstn = 1;
    #10;

    case (mode)
      0: begin // basic (short set)
        data_a = 36'sd0; data_b = 36'sd0; expected = data_a * data_b; ce = 1; valid_in = 1; @(posedge clk); #1; check_and_report(0);
        valid_in = 0; ce = 0; @(posedge clk);
        data_a = 36'sd1; data_b = 36'sd1; expected = data_a * data_b; ce = 1; valid_in = 1; @(posedge clk); #1; check_and_report(1);
      end

      1: begin // random vectors
        // Initialize RNG
        for (idx = 0; idx < NV; idx = idx + 1) begin
          r = {$random(seed), $random(seed)};
          data_a = r[35:0];
          r = {$random(seed), $random(seed)};
          data_b = r[35:0];

          expected = $signed(data_a) * $signed(data_b);
          ce = 1; valid_in = 1;
          @(posedge clk);
          #1;
          if (valid_out) begin
            if (mult_result !== expected) begin
              $display("ERROR: rand vec %0d: a=%0d b=%0d got=%0d exp=%0d", idx, data_a, data_b, mult_result, expected);
              errors = errors + 1;
            end
          end else begin
            $display("WARNING: rand vec %0d produced no valid_out", idx);
          end
          valid_in = 0; ce = 0;
        end
      end

      2: begin // boundary tests
        A[0] = MAX36; B[0] = MAX36;
        A[1] = MIN36; B[1] = MIN36;
        A[2] = MAX36; B[2] = 36'sd1;
        A[3] = MIN36; B[3] = 36'sd1;
        A[4] = MAX36; B[4] = -36'sd1;
        A[5] = -36'sd1; B[5] = MAX36;
        A[6] = 36'sd0; B[6] = MAX36;
        A[7] = -36'sd123456789; B[7] = 36'sd987654321;

        for (i = 0; i < 8; i = i + 1) begin
          data_a = A[i]; data_b = B[i]; expected = $signed(data_a) * $signed(data_b);
          ce = 1; valid_in = 1;
          @(posedge clk);
          #1;
          if (valid_out) begin
            if (mult_result !== expected) begin
              $display("ERROR: bound %0d: a=%0d b=%0d got=%0d exp=%0d", i, data_a, data_b, mult_result, expected);
              errors = errors + 1;
            end else begin
              $display("OK: bound %0d", i);
            end
          end
          valid_in = 0; ce = 0; @(posedge clk);
        end
      end

      3: begin // pipeline / back-to-back valid
        for (i = 0; i < NV; i = i + 1) begin
          r1 = {$random(seed), $random(seed)};
          r2 = {$random(seed), $random(seed)};
          data_a = r1[35:0]; data_b = r2[35:0];
          expected = $signed(data_a) * $signed(data_b);
          ce = 1; valid_in = 1; // keep valid high every cycle
          @(posedge clk);
          #1;
          if (valid_out) begin
            if (mult_result !== expected) begin
              $display("ERROR: pipe vec %0d: a=%0d b=%0d got=%0d exp=%0d", i, data_a, data_b, mult_result, expected);
              errors = errors + 1;
            end
          end else begin
            $display("WARNING: pipe vec %0d had no valid_out", i);
          end
        end
        // finish by deasserting valid
        valid_in = 0; ce = 0; @(posedge clk);
      end

      default: begin
        $display("Unknown mode %0d", mode);
      end
    endcase

    if (errors == 0) begin
      $display("ADVANCED MULT TEST PASSED");
      $finish;
    end else begin
      $display("ADVANCED MULT TEST FAILED: %0d errors", errors);
      $fatal;
    end
  end

  task check_and_report(input integer idx);
    begin
      #1;
      if (mult_result !== expected) begin
        $display("ERROR: vec %0d: a=%0d b=%0d got=%0d expected=%0d", idx, data_a, data_b, mult_result, expected);
        errors = errors + 1;
      end else begin
        $display("OK: vec %0d: a=%0d b=%0d result=%0d", idx, data_a, data_b, mult_result);
      end
    end
  endtask

endmodule

tests/tb_mult36x36.v
`timescale 1ns/1ps
module tb_mult36x36;
  reg clk = 0;
  always #5 clk = ~clk; // 10ns period

  reg rstn;
  reg ce;
  reg valid_in;
  reg signed [35:0] data_a;
  reg signed [35:0] data_b;
  wire valid_out;
  wire signed [71:0] mult_result;

  integer i;
  integer errors = 0;
  reg signed [71:0] expected;

  // Instantiate DUT
  mult36x36 uut (
    .clk(clk),
    .rstn(rstn),
    .ce(ce),
    .valid_in(valid_in),
    .data_a(data_a),
    .data_b(data_b),
    .valid_out(valid_out),
    .mult_result(mult_result)
  );

  // Test vectors
  localparam NV = 8;
  reg signed [35:0] a_vec [0:NV-1];
  reg signed [35:0] b_vec [0:NV-1];

  initial begin
    // define vectors (36-bit signed literals)
    a_vec[0] = 36'sd0;                  b_vec[0] = 36'sd0;
    a_vec[1] = 36'sd1;                  b_vec[1] = 36'sd1;
    a_vec[2] = -36'sd1;                 b_vec[2] = 36'sd1;
    a_vec[3] = 36'sd123456;             b_vec[3] = -36'sd789;
    a_vec[4] = 36'sd34359738367;        b_vec[4] = 36'sd1; // max positive * 1
    a_vec[5] = -36'sd34359738368;       b_vec[5] = 36'sd1; // min negative * 1
    a_vec[6] = 36'sd123456789;          b_vec[6] = 36'sd98765;
    a_vec[7] = -36'sd123456789;         b_vec[7] = -36'sd98765;

    $dumpfile("wave.vcd");
    $dumpvars(0, tb_mult36x36);

    // reset
    rstn = 0; ce = 0; valid_in = 0; data_a = 0; data_b = 0;
    #20; // two clock cycles
    rstn = 1;
    #10;

    // apply vectors
    for (i = 0; i < NV; i = i + 1) begin
      data_a = a_vec[i];
      data_b = b_vec[i];
      ce = 1;
      valid_in = 1;
      @(posedge clk);
      #1; // let registers settle

      expected = $signed(data_a) * $signed(data_b);
      if (mult_result !== expected) begin
        $display("ERROR: vec %0d: a=%0d b=%0d got=%0d expected=%0d time=%0t", i, data_a, data_b, mult_result, expected, $time);
        errors = errors + 1;
      end else begin
        $display("OK: vec %0d: a=%0d b=%0d result=%0d", i, data_a, data_b, mult_result);
      end

      // deassert valid for one cycle to separate vectors
      valid_in = 0;
      ce = 0;
      @(posedge clk);
    end

    if (errors == 0) begin
      $display("MULT TEST PASSED");
      $finish;
    end else begin
      $display("MULT TEST FAILED: %0d errors", errors);
      $fatal;
    end
  end
endmodule

wave.vcd
$date
	Fri Nov 28 03:38:54 2025
$end
$version
	Icarus Verilog
$end
$timescale
	1ps
$end
$scope module tb_mult36x36 $end
$var wire 1 ! valid_out $end
$var wire 72 " mult_result [71:0] $end
$var parameter 32 # NV $end
$var reg 1 $ ce $end
$var reg 1 % clk $end
$var reg 36 & data_a [35:0] $end
$var reg 36 ' data_b [35:0] $end
$var reg 72 ( expected [71:0] $end
$var reg 1 ) rstn $end
$var reg 1 * valid_in $end
$var integer 32 + errors [31:0] $end
$var integer 32 , i [31:0] $end
$scope module uut $end
$var wire 1 $ ce $end
$var wire 1 % clk $end
$var wire 36 - data_a [35:0] $end
$var wire 36 . data_b [35:0] $end
$var wire 1 ) rstn $end
$var wire 1 * valid_in $end
$var reg 72 / mult_result [71:0] $end
$var reg 1 ! valid_out $end
$upscope $end
$upscope $end
$scope module tb_mult36x36_advanced $end
$var wire 1 0 valid_out $end
$var wire 72 1 mult_result [71:0] $end
$var parameter 36 2 MAX36 $end
$var parameter 36 3 MIN36 $end
$var reg 1 4 ce $end
$var reg 1 5 clk $end
$var reg 36 6 data_a [35:0] $end
$var reg 36 7 data_b [35:0] $end
$var reg 72 8 expected [71:0] $end
$var reg 64 9 r [63:0] $end
$var reg 64 : r1 [63:0] $end
$var reg 64 ; r2 [63:0] $end
$var reg 1 < rstn $end
$var reg 1 = valid_in $end
$var integer 32 > NV [31:0] $end
$var integer 32 ? errors [31:0] $end
$var integer 32 @ i [31:0] $end
$var integer 32 A idx [31:0] $end
$var integer 32 B mode [31:0] $end
$var integer 32 C seed [31:0] $end
$scope module uut $end
$var wire 1 4 ce $end
$var wire 1 5 clk $end
$var wire 36 D data_a [35:0] $end
$var wire 36 E data_b [35:0] $end
$var wire 1 < rstn $end
$var wire 1 = valid_in $end
$var reg 72 F mult_result [71:0] $end
$var reg 1 0 valid_out $end
$upscope $end
$scope task check_and_report $end
$var integer 32 G idx [31:0] $end
$upscope $end
$upscope $end
$enddefinitions $end
$comment Show the parameter values. $end
$dumpall
b100000000000000000000000000000000000 3
b11111111111111111111111111111111111 2
b1000 #
$end
#0
$dumpvars
bx G
b0 F
b0 E
b0 D
b10010000101010011010100100100 C
b1 B
bx A
bx @
b0 ?
b100000000 >
0=
0<
bx ;
bx :
bx 9
bx 8
b0 7
b0 6
05
04
b0 1
00
b0 /
b0 .
b0 -
bx ,
b0 +
0*
0)
bx (
b0 '
b0 &
0%
0$
b0 "
0!
$end
#5000
15
1%
#10000
05
0%
#15000
15
1%
#20000
05
0%
1<
1)
#25000
15
1%
#30000
05
0%
1=
14
b1011011100111110110001100011011011110001011111100101101000100101000000 8
b11000110101111101111101101101101011 7
b11000110101111101111101101101101011 E
b11101100000010001010010101111000000 6
b11101100000010001010010101111000000 D
b1100001100000010111010001000011000110101111101111101101101101011 9
b10110101111101111101100100110000 C
b0 A
1*
1$
b0 ,
#35000
b1011011100111110110001100011011011110001011111100101101000100101000000 1
b1011011100111110110001100011011011110001011111100101101000100101000000 F
10
1!
15
1%
#36000
b110101111101100111010000001001110111011010100001000000001100110110 8
b111001111000100101001001110111110001 7
b111001111000100101001001110111110001 E
b110111001011010011101111100010010110 6
b110111001011010011101111100010010110 D
b1100011100111101110010101000111001111000100101001001110111110001 9
b11111000100101001001101111111100 C
b1 A
14
1=
0$
0*
b0 (
#40000
05
0%
#45000
b110101111101100111010000001001110111011010100001000000001100110110 1
b110101111101100111010000001001110111011010100001000000001100110110 F
b1 "
b1 /
1*
1$
b1 '
b1 .
b1 &
b1 -
b1 ,
15
1%
#46000
b111110111110101101101101011101100100011001001110001011110011011010111100 8
b1000001000100101100100101100010001 7
b1000001000100101100100101100010001 E
b110111111110010101000011001011111100 6
b110111111110010101000011001011111100 D
b10000100010100100000110100001000001000100101100100101100010001 9
b10001000100101100100100110001000 C
b10 A
14
1=
#50000
05
0%
#55000
b111110111110101101101101011101100100011001001110001011110011011010111100 1
b111110111110101101101101011101100100011001001110001011110011011010111100 F
15
1%
#56000
b110101000000000111010100100110010000111100101010000001110001010011111000 8
b101001011100000100100110111110111000 7
b101001011100000100100110111110111000 E
b11111001100101101111000011010011001 6
b11111001100101101111000011010011001 D
b1100010101000110110011001000101001011100000100100110111110111000 9
b11011100000100100110110111010100 C
b11 A
14
1=
0$
0*
b1 (
#60000
05
0%
#65000
b110101000000000111010100100110010000111100101010000001110001010011111000 1
b110101000000000111010100100110010000111100101010000001110001010011111000 F
b111111111111111111111111111111111111111111111111111111111111111111111111 "
b111111111111111111111111111111111111111111111111111111111111111111111111 /
1*
1$
b111111111111111111111111111111111111 &
b111111111111111111111111111111111111 -
b10 ,
15
1%
#66000
b11011011010001001001111110010010011000110001101000100100010000 8
b100101110000101010101011101011100 7
b100101110000101010101011101011100 E
b101110011101000101111101011100 6
b101110011101000101111101011100 D
b111100010100110001000111111000100101110000101010101011101011100 9
b10101110000101010101010011100000 C
b100 A
14
1=
#70000
05
0%
#75000
b11011011010001001001111110010010011000110001101000100100010000 1
b11011011010001001001111110010010011000110001101000100100010000 F
15
1%
#76000
b10011111011010100100010000100101111111000011111110101000101100000011 8
b1101110010111011100000110111100101 7
b1101110010111011100000110111100101 E
b1011100011100010101110011011000111 6
b1011100011100010101110011011000111 D
b10100110010001110001010101001101110010111011100000110111100101 9
b11110010111011100000101010101100 C
b101 A
14
1=
0$
0*
b111111111111111111111111111111111111111111111111111111111111111111111111 (
#80000
05
0%
#85000
b10011111011010100100010000100101111111000011111110101000101100000011 1
b10011111011010100100010000100101111111000011111110101000101100000011 F
b111111111111111111111111111111111111111111111010001100011011000011000000 "
b111111111111111111111111111111111111111111111010001100011011000011000000 /
1*
1$
b111111111111111111111111110011101011 '
b111111111111111111111111110011101011 .
b11110001001000000 &
b11110001001000000 -
b11 ,
15
1%
#86000
b111110001111111010100001001011100110101001011010010010011100011010010000 8
b111000001111001110100101110100011110 7
b111000001111001110100101110100011110 E
b1110011100001011000000110000111000 6
b1110011100001011000000110000111000 D
b101011100110010101010111010111000001111001110100101110100011110 9
b10001111001110100101101100111000 C
b110 A
14
1=
#90000
05
0%
#95000
b111110001111111010100001001011100110101001011010010010011100011010010000 1
b111110001111111010100001001011100110101001011010010010011100011010010000 F
15
1%
#96000
b1000100010001100110101010101000100110101001111010000000011010000010001 8
b10001011101101100101101010110111011 7
b10001011101101100101101010110111011 E
b11111010001101001010111101010100011 6
b11111010001101001010111101010100011 D
b1100001001110111100100101000010001011101101100101101010110111011 9
b11011101101100101101001010000100 C
b111 A
14
1=
0$
0*
b111111111111111111111111111111111111111111111010001100011011000011000000 (
#100000
05
0%
#105000
b1000100010001100110101010101000100110101001111010000000011010000010001 1
b1000100010001100110101010101000100110101001111010000000011010000010001 F
b11111111111111111111111111111111111 "
b11111111111111111111111111111111111 /
1*
1$
b1 '
b1 .
b11111111111111111111111111111111111 &
b11111111111111111111111111111111111 -
b100 ,
15
1%
#106000
b10111100111011100110001101110101001011011101110000001001001110001000 8
b100101001111101101101011111110011111 7
b100101001111101101101011111110011111 E
b111000111100000011011001111101111000 6
b111000111100000011011001111101111000 D
b110010011010000111110011100100101001111101101101011111110011111 9
b11001111101101101011110010010000 C
b1000 A
14
1=
#110000
05
0%
#115000
b10111100111011100110001101110101001011011101110000001001001110001000 1
b10111100111011100110001101110101001011011101110000001001001110001000 F
15
1%
#116000
b1000101111111110001011010101110111111100001101100100110010110001001 8
b110110100100110000010011001101001 7
b110110100100110000010011001101001 E
b1010010000101011111010001000100001 6
b1010010000101011111010001000100001 D
b110100010101101000110011101000110110100100110000010011001101001 9
b110100100110000010010101011100 C
b1001 A
14
1=
0$
0*
b11111111111111111111111111111111111 (
#120000
05
0%
#125000
b1000101111111110001011010101110111111100001101100100110010110001001 1
b1000101111111110001011010101110111111100001101100100110010110001001 F
b111111111111111111111111111111111111100000000000000000000000000000000000 "
b111111111111111111111111111111111111100000000000000000000000000000000000 /
1*
1$
b100000000000000000000000000000000000 &
b100000000000000000000000000000000000 -
b101 ,
15
1%
#126000
b11111000111101110101101001101010010001100010011111010100100110 8
b111111110011101001111101101011100111 7
b111111110011101001111101101011100111 E
b101011110101001101110111001011101010 6
b101011110101001101110111001011101010 D
b1001111110110011111011100011111111110011101001111101101011100111 9
b1110011101001111101100011101000 C
b1010 A
14
1=
#130000
05
0%
#135000
b11111000111101110101101001101010010001100010011111010100100110 1
b11111000111101110101101001101010010001100010011111010100100110 F
15
1%
#136000
b110101111001000010010011100000001101100100001111100000100001111100000110 8
b10101000101000000010110010110001010 7
b10101000101000000010110010110001010 E
b100001010011100111011011110110100111 6
b100001010011100111011011110110100111 D
b1011001011000011001101100110010101000101000000010110010110001010 9
b11000101000000010110001100110100 C
b1011 A
14
1=
0$
0*
b111111111111111111111111111111111111100000000000000000000000000000000000 (
#140000
05
0%
#145000
b110101111001000010010011100000001101100100001111100000100001111100000110 1
b110101111001000010010011100000001101100100001111100000100001111100000110 F
b10110001011011110011111011111100111011010001 "
b10110001011011110011111011111100111011010001 /
1*
1$
b11000000111001101 '
b11000000111001101 .
b111010110111100110100010101 &
b111010110111100110100010101 -
b110 ,
15
1%
#146000
b10011010001110110110111110110101110000010010001011110001001110010 8
b111100110101000101110001001101101010 7
b111100110101000101110001001101101010 E
b111001111010110100111110101111110101 6
b111001111010110100111110101111110101 D
b11110101010011011010000111100110101000101110001001101101010 9
b10110101000101110001000001000000 C
b1100 A
14
1=
#150000
05
0%
#155000
b10011010001110110110111110110101110000010010001011110001001110010 1
b10011010001110110110111110110101110000010010001011110001001110010 F
15
1%
#156000
b111111110111000010101000101110010001101011011111101111100001000010110000 8
b111111110111111011110111011111101 7
b111111110111111011110111011111101 E
b111110111000001100000010101001110000 6
b111110111000001100000010101001110000 D
b1100010100110110010110011000111111110111111011110111011111101 9
b1111110111111011110110000001100 C
b1101 A
14
1=
0$
0*
b10110001011011110011111011111100111011010001 (
#160000
05
0%
#165000
b111111110111000010101000101110010001101011011111101111100001000010110000 1
b111111110111000010101000101110010001101011011111101111100001000010110000 F
1*
1$
b111111111111111111100111111000110011 '
b111111111111111111100111111000110011 .
b111111111000101001000011001011101011 &
b111111111000101001000011001011101011 -
b111 ,
15
1%
#166000
b11010010100111011110011000010100001000100000110110001011110100000110 8
b1100001001011110011100010100010010 7
b1100001001011110011100010100010010 E
b10001010101100110010110010110101011 6
b10001010101100110010110010110101011 D
b1011100110011111010011100111001100001001011110011100010100010010 9
b10001001011110011100001010011000 C
b1110 A
14
1=
#170000
05
0%
#175000
b11010010100111011110011000010100001000100000110110001011110100000110 1
b11010010100111011110011000010100001000100000110110001011110100000110 F
15
1%
#176000
b10011001110000001110100011100100100000011111000111110001010010000 8
b111010010010110010010010000000100101 7
b111010010010110010010010000000100101 E
b111100101000011100110100101101010000 6
b111100101000011100110100101101010000 D
b1000011100100000101101100000111010010010110010010010000000100101 9
b10010110010010001111111100100 C
b1111 A
14
1=
0$
0*
#180000
05
0%
#185000
b10011001110000001110100011100100100000011111000111110001010010000 1
b10011001110000001110100011100100100000011111000111110001010010000 F
0!
b1000 ,
15
1%
